spotify_sync/__init__.py
spotify_sync/__main__.py
spotify_sync/appdirs_.py
spotify_sync/autoscan_.py
spotify_sync/backup/__init__.py
spotify_sync/backup/providers.py
spotify_sync/cli.py
spotify_sync/click_helper.py
spotify_sync/common.py
spotify_sync/config.py
spotify_sync/data/config.json.example
spotify_sync/data/config_schema.json
spotify_sync/data/config_schema_legacy.json
spotify_sync/dataclasses.py
spotify_sync/deemix_.py
spotify_sync/download.py
spotify_sync/errors.py
spotify_sync/io_.py
spotify_sync/log.py
spotify_sync/match.py
spotify_sync/metrics.py
spotify_sync/pushover_.py
spotify_sync/spotify_.py
spotify_sync/stats.py
spot_sync-1.1.1.dist-info/entry_points.txt
spot_sync-1.1.1.dist-info/LICENSE.md
spot_sync-1.1.1.dist-info/WHEEL
spot_sync-1.1.1.dist-info/METADATA
spot_sync-1.1.1.dist-info/RECORD
