Metadata-Version: 2.1
Name: spot-sync
Version: 1.1.1
Summary: A schedulable, configurable CLI downloader for Spotify accounts
Home-page: https://github.com/jbh-cloud/spotify_sync
License: MIT
Author: JBH
Author-email: admin@jbh.cloud
Requires-Python: >=3.8,<4.0
Classifier: License :: OSI Approved :: MIT License
Classifier: Programming Language :: Python :: 3
Classifier: Programming Language :: Python :: 3.10
Classifier: Programming Language :: Python :: 3.8
Classifier: Programming Language :: Python :: 3.9
Requires-Dist: appdirs (>=1.4.4,<2.0.0)
Requires-Dist: chump (>=1.6.0,<2.0.0)
Requires-Dist: click (>=8.1.3,<9.0.0)
Requires-Dist: click-option-group (>=0.5.3,<0.6.0)
Requires-Dist: deezer-py (>=1.3.7,<2.0.0)
Requires-Dist: flatdict (>=4.0.1,<5.0.0)
Requires-Dist: jsonschema (>=4.4.0,<5.0.0)
Requires-Dist: psutil (>=5.9.0,<6.0.0)
Requires-Dist: pywin32 (>=304,<305); sys_platform == "windows"
Requires-Dist: requests (>=2.25.1,<3.0.0)
Requires-Dist: spotipy (>=2.19.0,<3.0.0)
Requires-Dist: ss-deemx (>=3.6.8,<4.0.0)
Requires-Dist: tabulate (>=0.8.7,<0.9.0)
Project-URL: Documentation, https://docs.spotify-sync.jbh.cloud
Project-URL: Repository, https://github.com/jbh-cloud/spotify_sync
